README.md
setup.py
acapture/__init__.py
acapture/acapture.py
acapture.egg-info/PKG-INFO
acapture.egg-info/SOURCES.txt
acapture.egg-info/dependency_links.txt
acapture.egg-info/not-zip-safe
acapture.egg-info/requires.txt
acapture.egg-info/top_level.txt